camlab/__init__.py
camlab/camera.py
camlab/camera_torch.py
camlab-0.1.6.0.dist-info/licenses/LICENSE
camlab-0.1.6.0.dist-info/licenses/LICENSE1
camlab-0.1.6.0.dist-info/METADATA
camlab-0.1.6.0.dist-info/WHEEL
camlab-0.1.6.0.dist-info/top_level.txt
camlab-0.1.6.0.dist-info/RECORD
