Metadata-Version: 2.4
Name: camlab
Version: 0.1.6.0
Summary: A Python library for camera-related utilities and lab tools.
Author-email: Liwei Liao <your_email@example.com>
Maintainer-email: Liwei Liao <your_email@example.com>
License: Copyright (c) 2018 The Python Packaging Authority
Project-URL: Homepage, https://github.com/leviome/camlab
Project-URL: Repository, https://github.com/leviome/camlab
Project-URL: Issues, https://github.com/leviome/camlab/issues
Keywords: camera,computer-vision,lab,toolkit
Classifier: Programming Language :: Python :: 3
Classifier: License :: OSI Approved :: MIT License
Classifier: Operating System :: OS Independent
Requires-Python: >=3.8
License-File: LICENSE
License-File: LICENSE1
Requires-Dist: numpy>=1.22
Requires-Dist: torch>=2.0
Dynamic: license-file
